Metadata-Version: 1.1
Name: jloglevel
Version: 0.1.3
Summary: A command line tool for changing the logging level in JVM apps in runtime via Jolokia
Home-page: https://github.com/ivanyu/jloglevel
Author: Ivan Yurchenko
Author-email: ivan0yurchenko@gmail.com
License: Apache 2.0
Keywords: jmx jolokia logging jvm
Platform: UNKNOWN
Classifier: Development Status :: 4 - Beta
Classifier: Environment :: Console
Classifier: Intended Audience :: Developers
Classifier: Intended Audience :: System Administrators
Classifier: License :: OSI Approved :: Apache Software License
Classifier: Topic :: Software Development
